deep_tracking/__init__.py
deep_tracking/deep_tracking.py
deep_tracking-1.0.4.dist-info/LICENCE.txt
deep_tracking-1.0.4.dist-info/METADATA
deep_tracking-1.0.4.dist-info/WHEEL
deep_tracking-1.0.4.dist-info/top_level.txt
deep_tracking-1.0.4.dist-info/RECORD
